sedeuce/__init__.py
sedeuce/__main__.py
sedeuce/sed.py
sedeuce-0.1.1.dist-info/LICENSE.md
sedeuce-0.1.1.dist-info/METADATA
sedeuce-0.1.1.dist-info/WHEEL
sedeuce-0.1.1.dist-info/entry_points.txt
sedeuce-0.1.1.dist-info/top_level.txt
sedeuce-0.1.1.dist-info/RECORD
