Metadata-Version: 2.1
Name: sedeuce
Version: 0.1.1
Summary: A sed clone in Python with both CLI and library interfaces
Home-page: https://github.com/Tails86/sedeuce
Author: James Smith
Author-email: jmsmith86@gmail.com
License: UNKNOWN
Project-URL: Documentation, https://github.com/Tails86/sedeuce
Project-URL: Bug Reports, https://github.com/Tails86/sedeuce/issues
Project-URL: Source Code, https://github.com/Tails86/sedeuce
Keywords: sed,files,regex,replace
Platform: UNKNOWN
Classifier: Development Status :: 2 - Pre-Alpha
Classifier: Environment :: Console
Classifier: Intended Audience :: Information Technology
Classifier: Programming Language :: Python :: 3
Classifier: Programming Language :: Python :: 3.5
Classifier: Programming Language :: Python :: 3.6
Classifier: Programming Language :: Python :: 3.7
Classifier: Programming Language :: Python :: 3.8
Classifier: Programming Language :: Python :: 3.9
Classifier: Programming Language :: Python :: 3 :: Only
Classifier: License :: OSI Approved :: MIT License
Classifier: Operating System :: OS Independent
Requires-Python: >=3.5
Provides-Extra: dev
Requires-Dist: check-manifest ; extra == 'dev'
